setup.py
theslasher/__init__.py
theslasher/factory.py
theslasher.egg-info/PKG-INFO
theslasher.egg-info/SOURCES.txt
theslasher.egg-info/dependency_links.txt
theslasher.egg-info/entry_points.txt
theslasher.egg-info/not-zip-safe
theslasher.egg-info/requires.txt
theslasher.egg-info/top_level.txt