Metadata-Version: 1.0
Name: theslasher
Version: 0.1
Summary: removes trailing slashes
Home-page: http://k0s.org
Author: Jeff Hammel
Author-email: k0scist@gmail.com
License: UNKNOWN
Platform: UNKNOWN
